imbed/__init__.py
imbed/base.py
imbed/data_prep.py
imbed/imbed_project.py
imbed/imbed_types.py
imbed/oa_batch_embeddings.py
imbed/segmentation_util.py
imbed/stores_util.py
imbed/tools.py
imbed/util.py
imbed/vector_db.py
imbed/components/__init__.py
imbed/components/clusterization.py
imbed/components/components_util.py
imbed/components/planarization.py
imbed/components/segmentation.py
imbed/components/vectorization.py
imbed/examples/__init__.py
imbed/examples/batch_embeddings_examples.py
imbed/examples/imbed_box_01.py
imbed/examples/boxes/__init__.py
imbed/examples/boxes/planarize.py
imbed/mdat/__init__.py
imbed/tests/__init__.py
imbed/tests/test_imbed_project.py
imbed/tests/test_segmentation.py
imbed/tests/utils_for_tests.py
imbed-0.0.23.dist-info/LICENSE
imbed-0.0.23.dist-info/METADATA
imbed-0.0.23.dist-info/WHEEL
imbed-0.0.23.dist-info/top_level.txt
imbed-0.0.23.dist-info/RECORD
