Metadata-Version: 2.1
Name: imbed
Version: 0.0.23
Summary: Tools to work with embeddings
Home-page: https://github.com/thorwhalen/imbed
Author: Thor Whalen
License: mit
Platform: any
License-File: LICENSE
Requires-Dist: pandas
Requires-Dist: numpy
Requires-Dist: scikit-learn
Requires-Dist: dol
Requires-Dist: config2py
Requires-Dist: graze
Requires-Dist: lkj
Requires-Dist: umap-learn
Requires-Dist: tabled
Requires-Dist: oa
Requires-Dist: au
Requires-Dist: dill
